thymed/__init__.py
thymed/__main__.py
thymed/py.typed
thymed/thymed.tcss
thymed/thymer.py
thymed/thymer.tcss
thymed/tui.py
thymed-0.7.1.dist-info/LICENSE
thymed-0.7.1.dist-info/METADATA
thymed-0.7.1.dist-info/WHEEL
thymed-0.7.1.dist-info/entry_points.txt
thymed-0.7.1.dist-info/RECORD
