Metadata-Version: 2.3
Name: thymed
Version: 0.7.1
Summary: Thymed
Home-page: https://github.com/czarified/thymed
License: MIT
Author: Benjamin Crews
Author-email: aceF22@gmail.com
Requires-Python: >=3.10,<4.0
Classifier: Development Status :: 2 - Pre-Alpha
Classifier: License :: OSI Approved :: MIT License
Classifier: Programming Language :: Python :: 3
Classifier: Programming Language :: Python :: 3.10
Classifier: Programming Language :: Python :: 3.11
Classifier: Programming Language :: Python :: 3.12
Classifier: Programming Language :: Python :: 3.13
Requires-Dist: click (>=8.0.1)
Requires-Dist: openpyxl (>=3.0.10)
Requires-Dist: pandas (>2.2.0)
Requires-Dist: rich (>12.5.1)
Requires-Dist: textual (>0.38.1)
Requires-Dist: textual-datepicker (>=0.2.4)
Requires-Dist: textual-plotext (>0.2.1)
Requires-Dist: toml (>=0.10.2)
Project-URL: Changelog, https://github.com/czarified/thymed/releases
Project-URL: Documentation, https://thymed.readthedocs.io
Project-URL: Repository, https://github.com/czarified/thymed
